jonja/__init__.py
jonja/__init__.pyi
jonja/tools.py
jonja-0.1.6.dist-info/LICENSE
jonja-0.1.6.dist-info/METADATA
jonja-0.1.6.dist-info/WHEEL
jonja-0.1.6.dist-info/RECORD
