Metadata-Version: 2.3
Name: jonja
Version: 0.1.6
Summary: Simple jinja-based texts and objects render
License: MIT
Keywords: jinja,template,text
Author: lightmanLP
Author-email: liteman1000@gmail.com
Requires-Python: >=3.10,<4
Classifier: License :: OSI Approved :: MIT License
Classifier: Programming Language :: Python :: 3
Classifier: Programming Language :: Python :: 3.10
Classifier: Programming Language :: Python :: 3.11
Classifier: Programming Language :: Python :: 3.12
Classifier: Programming Language :: Python :: 3.13
Requires-Dist: aiofile (>=3.9.0,<4.0.0)
Requires-Dist: jinja2 (>=3.1.6,<4.0.0)
Requires-Dist: ruamel-yaml (>=0.18.14,<0.19.0)
Requires-Dist: utic-cache (>=2.2.1,<3.0.0)
Requires-Dist: yamt (>=1.0.0,<2.0.0)
Project-URL: repository, https://github.com/UT1C/jonja
